pyrainsty/__init__.py
pyrainsty/__version__.py
pyrainsty/ifparams.py
pyrainsty/iftest.py
pyrainsty/logger.py
pyrainsty/mysql_connect.py
pyrainsty/postgre_connect.py
pyrainsty/redis_connect.py
pyrainsty-0.0.15.dist-info/METADATA
pyrainsty-0.0.15.dist-info/WHEEL
pyrainsty-0.0.15.dist-info/top_level.txt
pyrainsty-0.0.15.dist-info/RECORD
