Metadata-Version: 2.1
Name: pyrainsty
Version: 0.0.15
Summary: The toolset.
Home-page: https://github.com/Rainstyed/pyrainsty
Author: Residual Mark
Author-email: rainstyd@sina.com
License: UNKNOWN
Platform: UNKNOWN
Classifier: Programming Language :: Python :: 3
Classifier: License :: OSI Approved :: MIT License
Classifier: Operating System :: OS Independent
Requires-Python: >=3.5
Requires-Dist: requests (>=2.22.0)
Requires-Dist: pymysql (>=0.9.3)
Requires-Dist: redis (>=3.3.8)
Requires-Dist: psycopg2-binary (>=2.8.3)
